aws_co/__init__.py
aws_co/cli.py
aws_co/config.py
aws_co/credentials.py
aws_co/utils.py
aws_co/commands/__init__.py
aws_co/commands/config.py
aws_co/commands/recent.py
aws_co/commands/run.py
aws_co/commands/setup.py
aws_co-0.5.0.dist-info/licenses/LICENSE
awsco/__init__.py
awsco/setup.py
awsco/aws_co/__init__.py
awsco/aws_co/cli.py
awsco/aws_co/config.py
awsco/aws_co/credentials.py
awsco/aws_co/utils.py
awsco/aws_co/commands/__init__.py
awsco/aws_co/commands/config.py
awsco/aws_co/commands/recent.py
awsco/aws_co/commands/run.py
awsco/aws_co/commands/setup.py
tests/__init__.py
tests/test_cli.py
aws_co-0.5.0.dist-info/METADATA
aws_co-0.5.0.dist-info/WHEEL
aws_co-0.5.0.dist-info/entry_points.txt
aws_co-0.5.0.dist-info/top_level.txt
aws_co-0.5.0.dist-info/RECORD
