Metadata-Version: 2.4
Name: aws-co
Version: 0.5.0
Summary: A CLI tool to assume AWS roles and run commands in target accounts
Home-page: https://github.com/trilogy-group/aws-co
Author: David Schwartz
Author-email: example@example.com
Project-URL: Bug Reports, https://github.com/trilogy-group/aws-co/issues
Project-URL: Source, https://github.com/trilogy-group/aws-co
Keywords: aws,cli,role,assume,credentials,iam,sts
Classifier: Development Status :: 4 - Beta
Classifier: Intended Audience :: Developers
Classifier: Intended Audience :: System Administrators
Classifier: License :: OSI Approved :: MIT License
Classifier: Programming Language :: Python :: 3
Classifier: Programming Language :: Python :: 3.6
Classifier: Programming Language :: Python :: 3.7
Classifier: Programming Language :: Python :: 3.8
Classifier: Programming Language :: Python :: 3.9
Classifier: Topic :: System :: Systems Administration
Classifier: Topic :: Utilities
Requires-Python: >=3.6
License-File: LICENSE
Requires-Dist: click>=8.0.0
Dynamic: author
Dynamic: author-email
Dynamic: classifier
Dynamic: description
Dynamic: description-content-type
Dynamic: home-page
Dynamic: keywords
Dynamic: license-file
Dynamic: project-url
Dynamic: requires-dist
Dynamic: requires-python
Dynamic: summary
